{
    "variants": {
        "waterlogged=false": [
            { "model": "block/red_sand" },
            { "model": "block/red_sand", "y": 90 },
            { "model": "block/red_sand", "y": 180 },
            { "model": "block/red_sand", "y": 270 }
        ],
        "waterlogged=true": [
            { "model": "cottontweaks:block/red_sand_wet" },
            { "model": "cottontweaks:block/red_sand_wet", "y": 90 },
            { "model": "cottontweaks:block/red_sand_wet", "y": 180 },
            { "model": "cottontweaks:block/red_sand_wet", "y": 270 }
        ]
    }
}
